astropyfr
