Metadata-Version: 1.1
Name: astropyfr
Version: 0.0.1.dev9
Summary: Python library for Traditional Astrology with export json
Home-page: https://github.com/stephaneworkspace/astro_py
Author: Stéphane Bressani
Author-email: s.bressani@bluewin.ch
License: GPL
Keywords: Astrology,Traditional Astrology
Platform: UNKNOWN
Classifier: Programming Language :: Python :: 3
Classifier: License :: OSI Approved :: MIT License
Classifier: Operating System :: OS Independent
Classifier: Development Status :: 4 - Beta
Classifier: Environment :: Other Environment
Classifier: Intended Audience :: Developers
Classifier: Intended Audience :: Science/Research
Classifier: Topic :: Software Development :: Libraries :: Python Modules
